martix/__init__.py
martix/client.py
martix/events.py
martix/exceptions.py
martix/types.py
martix/utils.py
martix-1.2.2.dist-info/METADATA
martix-1.2.2.dist-info/WHEEL
martix-1.2.2.dist-info/licenses/LICENSE
martix-1.2.2.dist-info/RECORD
