Metadata-Version: 2.4
Name: martix
Version: 1.2.2
Summary: A python wrapper for matrix bots
Project-URL: github, https://github.com/daradege/martix
Project-URL: website, https://martix.daradege.ir
Author-email: Ali Safamanesh <daradege@proton.me>
License: MIT License
License-File: LICENSE
Classifier: License :: OSI Approved :: MIT License
Classifier: Operating System :: OS Independent
Classifier: Programming Language :: Python :: 3
Requires-Python: >=3.9
Requires-Dist: aiofiles>=23.0.0
Requires-Dist: markdown
Requires-Dist: matrix-nio[e2e]
Requires-Dist: pillow>=10.0.0
